CMakeLists.txt
LICENSE
MANIFEST.in
README.md
setup.py
bgslibrary/algorithms/AdaptiveBackgroundLearning.cpp
bgslibrary/algorithms/AdaptiveBackgroundLearning.h
bgslibrary/algorithms/AdaptiveSelectiveBackgroundLearning.cpp
bgslibrary/algorithms/AdaptiveSelectiveBackgroundLearning.h
bgslibrary/algorithms/CodeBook.cpp
bgslibrary/algorithms/CodeBook.h
bgslibrary/algorithms/DPAdaptiveMedian.cpp
bgslibrary/algorithms/DPAdaptiveMedian.h
bgslibrary/algorithms/DPEigenbackground.cpp
bgslibrary/algorithms/DPEigenbackground.h
bgslibrary/algorithms/DPGrimsonGMM.cpp
bgslibrary/algorithms/DPGrimsonGMM.h
bgslibrary/algorithms/DPMean.cpp
bgslibrary/algorithms/DPMean.h
bgslibrary/algorithms/DPPratiMediod.cpp
bgslibrary/algorithms/DPPratiMediod.h
bgslibrary/algorithms/DPTexture.cpp
bgslibrary/algorithms/DPTexture.h
bgslibrary/algorithms/DPWrenGA.cpp
bgslibrary/algorithms/DPWrenGA.h
bgslibrary/algorithms/DPZivkovicAGMM.cpp
bgslibrary/algorithms/DPZivkovicAGMM.h
bgslibrary/algorithms/FrameDifference.cpp
bgslibrary/algorithms/FrameDifference.h
bgslibrary/algorithms/FuzzyChoquetIntegral.cpp
bgslibrary/algorithms/FuzzyChoquetIntegral.h
bgslibrary/algorithms/FuzzySugenoIntegral.cpp
bgslibrary/algorithms/FuzzySugenoIntegral.h
bgslibrary/algorithms/GMG.cpp
bgslibrary/algorithms/GMG.h
bgslibrary/algorithms/IBGS.h
bgslibrary/algorithms/IndependentMultimodal.cpp
bgslibrary/algorithms/IndependentMultimodal.h
bgslibrary/algorithms/KDE.cpp
bgslibrary/algorithms/KDE.h
bgslibrary/algorithms/KNN.cpp
bgslibrary/algorithms/KNN.h
bgslibrary/algorithms/LBAdaptiveSOM.cpp
bgslibrary/algorithms/LBAdaptiveSOM.h
bgslibrary/algorithms/LBFuzzyAdaptiveSOM.cpp
bgslibrary/algorithms/LBFuzzyAdaptiveSOM.h
bgslibrary/algorithms/LBFuzzyGaussian.cpp
bgslibrary/algorithms/LBFuzzyGaussian.h
bgslibrary/algorithms/LBMixtureOfGaussians.cpp
bgslibrary/algorithms/LBMixtureOfGaussians.h
bgslibrary/algorithms/LBP_MRF.cpp
bgslibrary/algorithms/LBP_MRF.h
bgslibrary/algorithms/LBSimpleGaussian.cpp
pybgs.egg-info/PKG-INFO
pybgs.egg-info/SOURCES.txt
pybgs.egg-info/dependency_links.txt
pybgs.egg-info/not-zip-safe
pybgs.egg-info/top_level.txt
