Metadata-Version: 2.1
Name: pybgs
Version: 3.3.0.post2
Summary: Official Python wrapper for BGSLibrary
Home-page: https://github.com/andrewssobral/bgslibrary
Author: Andrews Sobral
Author-email: andrewssobral@gmail.com
License: MIT
Keywords: BGSLibrary,Background Subtraction,Computer Vision,Machine Learning
Platform: UNKNOWN
